setup.cfg
setup.py
debug_template/__init__.py
debug_template/templatetags/__init__.py
debug_template/templatetags/debug.py
django_debug_template.egg-info/PKG-INFO
django_debug_template.egg-info/SOURCES.txt
django_debug_template.egg-info/dependency_links.txt
django_debug_template.egg-info/requires.txt
django_debug_template.egg-info/top_level.txt