Metadata-Version: 1.0
Name: django-debug-template
Version: 0.1.6
Summary: Project that helps you to debug django template context
Home-page: https://github.com/t0ster/django-debug-template
Author: Roman Dolgiy
Author-email: roman@bravetstudio.com
License: UNKNOWN
Platform: UNKNOWN
